flask_session_plus/__init__.py
flask_session_plus/backends.py
flask_session_plus/core.py
flask_session_plus/session.py
test/__init__.py
test/auth.py
test/flask_app.py
test/models.py
flask_session_plus-0.6.2.dist-info/LICENSE
flask_session_plus-0.6.2.dist-info/METADATA
flask_session_plus-0.6.2.dist-info/WHEEL
flask_session_plus-0.6.2.dist-info/top_level.txt
flask_session_plus-0.6.2.dist-info/RECORD
