Metadata-Version: 2.1
Name: flask-session-plus
Version: 0.6.2
Summary: Flask Multiple Sessions Interface (combine multiple sessions with different backends)
Home-page: https://github.com/janscas/flask-session-plus
Author: Janscas
Author-email: janscas@users.noreply.github.com
Maintainer: Janscas
Maintainer-email: janscas@users.noreply.github.com
License: Mit License
Platform: UNKNOWN
Classifier: Development Status :: 4 - Beta
Classifier: Intended Audience :: Developers
Classifier: License :: OSI Approved :: Apache Software License
Classifier: Topic :: Office/Business :: Office Suites
Classifier: Topic :: Software Development :: Libraries
Classifier: Programming Language :: Python
Classifier: Programming Language :: Python :: 3 :: Only
Classifier: Programming Language :: Python :: 3.4
Classifier: Programming Language :: Python :: 3.5
Classifier: Programming Language :: Python :: 3.6
Classifier: Programming Language :: Python :: 3.7
Classifier: Programming Language :: Python :: 3.8
Classifier: Operating System :: OS Independent
Requires-Python: >=3.4
